arb_watchdog/__init__.py
arb_watchdog/cli.py
arb_watchdog/config.py
arb_watchdog/process_data.py
arb_watchdog/process_watcher.py
arb_watchdog-1.0.1.dist-info/METADATA
arb_watchdog-1.0.1.dist-info/WHEEL
arb_watchdog-1.0.1.dist-info/entry_points.txt
arb_watchdog-1.0.1.dist-info/top_level.txt
arb_watchdog-1.0.1.dist-info/RECORD
