Metadata-Version: 2.1
Name: arb-watchdog
Version: 1.0.1
Summary: A process monitoring and alerting tool that keeps an up-to-date status of processes in Redis
Home-page: https://github.com/Acid3croco/arb-trops-services
Author: arb
Author-email: arb.trops@gmail.com
Requires-Dist: watchdog
Requires-Dist: redis
Requires-Dist: tabulate
Requires-Dist: colorama
Requires-Dist: psutil
